authenticatorpy/__init__.py
authenticatorpy/__main__.py
authenticatorpy/authenticator.py
authenticatorpy-0.3.1.dist-info/COPYING
authenticatorpy-0.3.1.dist-info/LICENSE
authenticatorpy-0.3.1.dist-info/METADATA
authenticatorpy-0.3.1.dist-info/NOTICE
authenticatorpy-0.3.1.dist-info/WHEEL
authenticatorpy-0.3.1.dist-info/top_level.txt
authenticatorpy-0.3.1.dist-info/RECORD
